LICENSE
MANIFEST.in
README.rst
setup.py
visaxrated/__init__.py
visaxrated.egg-info/PKG-INFO
visaxrated.egg-info/SOURCES.txt
visaxrated.egg-info/dependency_links.txt
visaxrated.egg-info/not-zip-safe
visaxrated.egg-info/requires.txt
visaxrated.egg-info/top_level.txt