Metadata-Version: 1.1
Name: visaxrated
Version: 0.2.0
Summary: Get exchange rates for Visa.
Home-page: https://github.com/aino/visaxrated
Author: Mikko Hellsing
Author-email: mikko@aino.se
License: BSD
Platform: UNKNOWN
Classifier: Development Status :: 3 - Alpha
Classifier: Environment :: Web Environment
Classifier: Intended Audience :: Developers
Classifier: License :: OSI Approved :: BSD License
Classifier: Operating System :: OS Independent
Classifier: Programming Language :: Python
